dbpd/__init__.py
dbpd/access.py
dbpd/dbpd.py
dbpd/mysql.py
dbpd/oracle.py
dbpd/postgres.py
dbpd/sqlite.py
dbpd-1.1.dist-info/LICENSE.txt
dbpd-1.1.dist-info/METADATA
dbpd-1.1.dist-info/WHEEL
dbpd-1.1.dist-info/top_level.txt
dbpd-1.1.dist-info/RECORD
