Metadata-Version: 2.1
Name: dbpd
Version: 1.1
Summary: Python module for establishing a working relationship between relational databases and Pandas DataFrames
Home-page: https://github.com/zacharybeebe/dbpd
Author: Zach Beebe
Author-email: z.beebe@yahoo.com
License: MIT
Keywords: database,pandas,DataFrameAccess,MySQL,Oracle,Postgres,SQLite
Classifier: Development Status :: 5 - Production/Stable
Classifier: Intended Audience :: Science/Research
Classifier: Programming Language :: Python :: 3
Classifier: License :: OSI Approved :: MIT License
Classifier: Operating System :: OS Independent
Requires-Python: >=3.8
License-File: LICENSE.txt
Requires-Dist: cffi
Requires-Dist: cryptography
Requires-Dist: greenlet
Requires-Dist: numpy
Requires-Dist: pandas
Requires-Dist: pycparser
Requires-Dist: pyodbc
Requires-Dist: python-dateutil
Requires-Dist: pytz
Requires-Dist: pywin32
Requires-Dist: six
Requires-Dist: SQLAlchemy
Requires-Dist: typing-extensions
Requires-Dist: tzdata
